{
    "category": "BOUNDARIES",
    "feature_classes": [
        "SGID.BOUNDARIES.Wilderness_BLMWSAs",
        "SGID.BOUNDARIES.Wilderness_BLMSuitability",
        "SGID.BOUNDARIES.Wilderness_BLM98Reinventory",
        "SGID.BOUNDARIES.USFSRoadlessInventory",
        "SGID.BOUNDARIES.USFSWildernessAreas",
        "SGID.CADASTRE.LandOwnership",
        "SGID.PLANNING.WildernessProp_BLM",
        "SGID.PLANNING.WildernessProp_HR1500",
        "SGID.PLANNING.WildernessProp_HR1745",
        "SGID.PLANNING.WildernessProp_NineCo1995",
        "SGID.PLANNING.WildernessProp_RedRock",
        "SGID.PLANNING.WildernessProp_UWA1995",
        "SGID.PLANNING.WildernessProp_UWC1989",
        "SGID.PLANNING.WildernessProp_UWC1995",
        "SGID.PLANNING.WildernessProp_UWC2008",
        "SGID.PLANNING.WildernessProp_WashingtonCo",
        "SGID.PLANNING.WildernessProp_WDesert1999"
    ],
    "gdb_id": "0ByStJjVZ7c7mejBaTnhpQWVaWUE",
    "name": "Wilderness_ProtectedLandsAndProposals",
    "parent_ids": [
        "0ByStJjVZ7c7mV2JyekFMdHVqbEE"
    ],
    "shape_id": "0ByStJjVZ7c7mdl8xbXJMWjdSRTA"
}
